amper_api/__init__.py
amper_api/auth.py
amper_api/backend.py
amper_api/cashdocument.py
amper_api/complaint.py
amper_api/customer.py
amper_api/customertask.py
amper_api/document.py
amper_api/log.py
amper_api/order.py
amper_api/product.py
amper_api/promotion.py
amper_api/salesrepresentative.py
amper_api/schedulerentry.py
amper_api/settlement.py
amper_api/user.py
amper_api-0.1.16.dist-info/METADATA
amper_api-0.1.16.dist-info/WHEEL
amper_api-0.1.16.dist-info/top_level.txt
amper_api-0.1.16.dist-info/RECORD
